django_gcp_iam_auth/__init__.py
django_gcp_iam_auth/postgresql/__init__.py
django_gcp_iam_auth/postgresql/base.py
django_gcp_iam_auth-0.0.4.dist-info/METADATA
django_gcp_iam_auth-0.0.4.dist-info/WHEEL
django_gcp_iam_auth-0.0.4.dist-info/licenses/LICENSE
django_gcp_iam_auth-0.0.4.dist-info/RECORD
