Metadata-Version: 2.1
Name: django_gcp_iam_auth
Version: 0.0.4
Summary: Allow Django's database wrappers to work with Google Cloud SQL's IAM Auth
Project-URL: Homepage, https://github.com/rcleveng/django_gcp_iam_auth
Project-URL: Issues, https://github.com/rcleveng/django_gcp_iam_auth/issues
Author-email: Rob Clevenger <rob+django_gcp_iam_auth@robsite.org>
License-File: LICENSE
Classifier: License :: OSI Approved :: Apache Software License
Classifier: Operating System :: OS Independent
Classifier: Programming Language :: Python :: 3
Requires-Python: >=3.7
Requires-Dist: django>4.0
Requires-Dist: google-auth
Requires-Dist: requests
